<?xml version="1.0" encoding="UTF-8"?>
<!DOCTYPE stylesheet SYSTEM "file:///C:/Users/nlutt/Documents/Websites/tools/entities.dtd">
<fr:recipe xmlns:fr="http://fruschtique.de/ns/recipe" xmlns:xsi="http://www.w3.org/2001/XMLSchema-instance" xsi:schemaLocation="http://fruschtique.de/ns/recipe ../../../tools/recipe.xsd" rcpID="fr-fdf14699-ebb2-4735-9b36-e951e58b0a2d">
<fr:meta><fr:book>kochbuch</fr:book><fr:chapter>06 Nudeln</fr:chapter></fr:meta><fr:recipeName>Bratnudeln asiatisch</fr:recipeName><fr:recipeKeywords></fr:recipeKeywords><fr:recipeIntro><fr:introText>Der Wok ruft! Nudeln mal ohne Tomatensauce.</fr:introText></fr:recipeIntro><fr:recipeIngredients><fr:igdtList><fr:igdtListName>Würzgemüse</fr:igdtListName><fr:igdtListLine><fr:igdtQuantity>2</fr:igdtQuantity><fr:igdtName ref="">Zwiebeln</fr:igdtName></fr:igdtListLine><fr:igdtListLine><fr:igdtQuantity>3</fr:igdtQuantity><fr:igdtName ref="">Knoblauchzehen</fr:igdtName></fr:igdtListLine><fr:igdtListLine><fr:igdtQuantity>3</fr:igdtQuantity><fr:igdtName ref="">Karotten</fr:igdtName></fr:igdtListLine><fr:igdtListLine><fr:igdtQuantity>2 Stangen</fr:igdtQuantity><fr:igdtName ref="">Staudensellerie</fr:igdtName></fr:igdtListLine><fr:igdtListLine><fr:igdtQuantity>&amp;frac14;</fr:igdtQuantity><fr:igdtName ref="">Spitzkohl</fr:igdtName></fr:igdtListLine><fr:igdtListLine><fr:igdtQuantity>2 EL</fr:igdtQuantity><fr:igdtName ref="">eingelegter Ingwer</fr:igdtName></fr:igdtListLine><fr:igdtListLine><fr:igdtQuantity></fr:igdtQuantity><fr:igdtName ref="">Öl zum Braten</fr:igdtName></fr:igdtListLine></fr:igdtList></fr:recipeIngredients><fr:recipeInstructions/><fr:recipeSideDish></fr:recipeSideDish><fr:recipeOrigin></fr:recipeOrigin><fr:recipeSeeAlso></fr:recipeSeeAlso><fr:recipeLicense></fr:recipeLicense></fr:recipe>