<?xml version="1.0" encoding="UTF-8"?><!DOCTYPE stylesheet SYSTEM "../../../tools/entities.dtd"><fr:recipe xmlns:fr="http://fruschtique.de/ns/recipe" xmlns:xsi="http://www.w3.org/2001/XMLSchema-instance" xsi:schemaLocation="http://fruschtique.de/ns/recipe file:///c:/Users/nlutt/Documents/Websites/tools/recipe.xsd" rcpID="fr-4e5b578e-0ddc-4904-9f37-db3628327f55">
<fr:meta><fr:book>kochbuch</fr:book><fr:chapter>07 Vegetarisch</fr:chapter></fr:meta><fr:recipeName>Lauchtorte</fr:recipeName><fr:recipeKeywords>Lauch</fr:recipeKeywords><fr:recipeIntro/><fr:recipeIngredients><fr:igdtList><fr:igdtListName>Hefeteig</fr:igdtListName><fr:igdtListLine><fr:igdtQuantity></fr:igdtQuantity><fr:igdtName ref="">[Hefeteig](Hefeteig.html) von 300 g Mehl</fr:igdtName></fr:igdtListLine></fr:igdtList><fr:igdtList><fr:igdtListName>Lauchfüllung</fr:igdtListName><fr:igdtListLine><fr:igdtQuantity>4 - 5</fr:igdtQuantity><fr:igdtName ref="lauch">Lauchstangen</fr:igdtName></fr:igdtListLine><fr:igdtListLine><fr:igdtQuantity>1 EL</fr:igdtQuantity><fr:igdtName ref="">Öl</fr:igdtName></fr:igdtListLine><fr:igdtListLine><fr:igdtQuantity></fr:igdtQuantity><fr:igdtName ref="sojasauce">Sojasauce</fr:igdtName></fr:igdtListLine><fr:igdtListLine><fr:igdtQuantity></fr:igdtQuantity><fr:igdtName ref="muskat">Muskat</fr:igdtName></fr:igdtListLine><fr:igdtListLine><fr:igdtQuantity></fr:igdtQuantity><fr:igdtName ref="">Salz, Pfeffer</fr:igdtName></fr:igdtListLine></fr:igdtList><fr:igdtList><fr:igdtListName>Deckel</fr:igdtListName><fr:igdtListLine><fr:igdtQuantity>125 g</fr:igdtQuantity><fr:igdtName ref="frischkäse">Kräuter-Philadelphia</fr:igdtName></fr:igdtListLine><fr:igdtListLine><fr:igdtQuantity>200 g</fr:igdtQuantity><fr:igdtName ref="schmand">saure Sahne</fr:igdtName></fr:igdtListLine><fr:igdtListLine><fr:igdtQuantity>2 EL</fr:igdtQuantity><fr:igdtName ref="joghurt">Joghurt 3,5% Fett</fr:igdtName></fr:igdtListLine><fr:igdtListLine><fr:igdtQuantity>1</fr:igdtQuantity><fr:igdtName ref="ei">Ei</fr:igdtName></fr:igdtListLine><fr:igdtListLine><fr:igdtQuantity></fr:igdtQuantity><fr:igdtName ref="worcester">Worcestershire-Sauce</fr:igdtName></fr:igdtListLine><fr:igdtListLine><fr:igdtQuantity></fr:igdtQuantity><fr:igdtName ref="sherry">trockener Sherry</fr:igdtName></fr:igdtListLine><fr:igdtListLine><fr:igdtQuantity>1</fr:igdtQuantity><fr:igdtName ref="knoblauch">Knoblauchzehe</fr:igdtName></fr:igdtListLine><fr:igdtListLine><fr:igdtQuantity></fr:igdtQuantity><fr:igdtName ref="">Salz, Pfeffer</fr:igdtName></fr:igdtListLine></fr:igdtList></fr:recipeIngredients><fr:recipeInstructions><fr:instruction><fr:instrStepName>Vorbereitung</fr:instrStepName><fr:instrStepText>Lauch waschen, das Weiße in Ringe schneiden. Das Grüne großzügig einkürzen, aber nicht verachten.</fr:instrStepText></fr:instruction><fr:instruction><fr:instrStepName>Füllung</fr:instrStepName><fr:instrStepText>Das Öl erhitzen (nicht zu doll), Lauch in den Topf geben, salzen und unter ständigem Wenden andünsten, bis der Lauch Wasser gezogen hat. 2 – 3 kräftige Spritzer Sojasauce dazu und den Deckel auf den Topf. Muskat reiben und auch dazu. Wenn’s brennt, tut man Wasser hinzu, wenn man’s kann, braucht man’s nicht. Der Lauch ist nach ca. 10 – 15 min gar; Biolauch dauert möglicherweise länger. Beiseite stellen.</fr:instrStepText></fr:instruction><fr:instruction><fr:instrStepName>Deckel</fr:instrStepName><fr:instrStepText>Alle Zutaten miteinander vermischen. Am besten fängt man damit an, daß man den Käse mit der sauren Sahne glattrührt. Mit Worcestershire-Sauce, Salz und Pfeffer abschmecken.</fr:instrStepText></fr:instruction><fr:instruction><fr:instrStepName>Fertigstellung</fr:instrStepName><fr:instrStepText>Eine Springform mit dem aufgegangenen Hefeteig ausschlagen. Lauch einfüllen, wobei die Lauchbrühe möglichst im Topf bleiben sollte. Den Deckel gleichmäßig darüber verteilen, und ab damit in den Ofen. Nach ca. 20 min sollte der Deckel angebräunt sein. Während der Wartezeit darf sich die tüchtige Köchin die lauwarme Lauchbrühe als köstliche Vorsuppe gönnen. Davon würde ich niemandem abgeben.</fr:instrStepText></fr:instruction></fr:recipeInstructions><fr:recipeSideDish>ein sizilianischer Nero d’Avola oder ein fruchtiger Chardonnay </fr:recipeSideDish><fr:recipeOrigin></fr:recipeOrigin><fr:recipeSeeAlso></fr:recipeSeeAlso><fr:recipeLicense></fr:recipeLicense></fr:recipe>