<?xml version="1.0" encoding="UTF-8"?>
<!DOCTYPE stylesheet SYSTEM "file:///C:/Users/nlutt/Documents/Websites/tools/entities.dtd">
<fr:recipe xmlns:fr="http://fruschtique.de/ns/recipe" xmlns:xsi="http://www.w3.org/2001/XMLSchema-instance" xsi:schemaLocation="http://fruschtique.de/ns/recipe ../../../tools/recipe.xsd" rcpID="fr-29839fcf-35d2-4ee4-9a0d-a4e46251ad7f">
    <fr:meta>
        <fr:book>kochbuch</fr:book>
        <fr:chapter>05 Fisch</fr:chapter>
    </fr:meta>
    <fr:recipeName>Moules à la provençale</fr:recipeName>
    <fr:recipeKeywords>Muscheln</fr:recipeKeywords>
    <fr:recipeIntro>
        <fr:introText>Wer’s nicht weiß: Moules sind Miesmuscheln … Bei uns gibt’s die nur im Winter.</fr:introText>
        <fr:introText>Zu beachten sind die folgenden Regeln: Muscheln mit zerbrochener Schale sofort wegwerfen. Geöffnete Muscheln nur dann verwenden, wenn sie sich von alleine wieder schließen, nachdem man sie einmal kräftig auf den Tisch geklopft hat. Muscheln, die sich beim Garen nicht geöffnet haben, sollte man ebenfalls wegwerfen.</fr:introText>
        <fr:introText>Die angegebene Menge reicht für 4 Personen.</fr:introText>
    </fr:recipeIntro>
    <fr:recipeIngredients>
        <fr:igdtList>
            <fr:igdtListName/>
            <fr:igdtListLine>
                <fr:igdtQuantity>3 kg</fr:igdtQuantity>
                <fr:igdtName ref="">Miesmuscheln</fr:igdtName>
            </fr:igdtListLine>
            <fr:igdtListLine>
                <fr:igdtQuantity>1 Stange</fr:igdtQuantity>
                <fr:igdtName ref="">Lauch</fr:igdtName>
            </fr:igdtListLine>
            <fr:igdtListLine>
                <fr:igdtQuantity>4</fr:igdtQuantity>
                <fr:igdtName ref="">Karotten</fr:igdtName>
            </fr:igdtListLine>
            <fr:igdtListLine>
                <fr:igdtQuantity>¼</fr:igdtQuantity>
                <fr:igdtName ref="">Sellerieknolle</fr:igdtName>
            </fr:igdtListLine>
            <fr:igdtListLine>
                <fr:igdtQuantity>2 Stangen</fr:igdtQuantity>
                <fr:igdtName ref="">Staudensellerie</fr:igdtName>
            </fr:igdtListLine>
            <fr:igdtListLine>
                <fr:igdtQuantity>3</fr:igdtQuantity>
                <fr:igdtName ref="">Zwiebeln</fr:igdtName>
            </fr:igdtListLine>
            <fr:igdtListLine>
                <fr:igdtQuantity>5</fr:igdtQuantity>
                <fr:igdtName ref="">Knoblauchzehen</fr:igdtName>
            </fr:igdtListLine>
            <fr:igdtListLine>
                <fr:igdtQuantity>100 ml</fr:igdtQuantity>
                <fr:igdtName ref="">Olivenöl</fr:igdtName>
            </fr:igdtListLine>
            <fr:igdtListLine>
                <fr:igdtQuantity>2</fr:igdtQuantity>
                <fr:igdtName ref="">rote Chilischoten</fr:igdtName>
            </fr:igdtListLine>
            <fr:igdtListLine>
                <fr:igdtQuantity>1</fr:igdtQuantity>
                <fr:igdtName ref="">Zweig Rosmarin</fr:igdtName>
            </fr:igdtListLine>
            <fr:igdtListLine>
                <fr:igdtQuantity>1 Bund</fr:igdtQuantity>
                <fr:igdtName ref="">Thymian</fr:igdtName>
            </fr:igdtListLine>
            <fr:igdtListLine>
                <fr:igdtQuantity>6</fr:igdtQuantity>
                <fr:igdtName ref="">Lorbeerblätter</fr:igdtName>
            </fr:igdtListLine>
            <fr:igdtListLine>
                <fr:igdtQuantity>2 gr. Dosen</fr:igdtQuantity>
                <fr:igdtName ref="">geschälte Tomaten</fr:igdtName>
            </fr:igdtListLine>
            <fr:igdtListLine>
                <fr:igdtQuantity/>
                <fr:igdtName ref="">Salz</fr:igdtName>
            </fr:igdtListLine>
            <fr:igdtListLine>
                <fr:igdtQuantity>1 l</fr:igdtQuantity>
                <fr:igdtName ref="">trockener Weißwein</fr:igdtName>
            </fr:igdtListLine>
        </fr:igdtList>
    </fr:recipeIngredients>
    <fr:recipeInstructions>
        <fr:instruction>
            <fr:instrStepName>Vorbereitung</fr:instrStepName>
            <fr:instrStepText>Muscheln gut unter kaltem Wasser sauber putzen. Lauch, Karotten, Sellerie und Zwiebeln putzen und in kleine Würfel schneiden. Knoblauchzehen scheibeln.</fr:instrStepText>
        </fr:instruction>
        <fr:instruction>
            <fr:instrStepName>Zubereitung</fr:instrStepName>
            <fr:instrStepText>Öl in einem hohen Topf erhitzen und das gewürfelte Gemüse gut anrösten. Anschließend die Kräuter, Gewürze, Knoblauch und Tomaten dazugeben und etwas einkochen lassen (12 – 15 min). Wein zugeben und aufkochen lassen. Sehr sparsam salzen.</fr:instrStepText>
            <fr:instrStepText>Dann die Muscheln zugeben und zugedeckt ca. 8 – 10 min garen. Den Topf zwischendurch rütteln, damit sich die Muscheln mit der Sauce vermischen.</fr:instrStepText>
        </fr:instruction>
    </fr:recipeInstructions>
    <fr:recipeSideDish>Baguette und, naja, und trockener Weißwein … </fr:recipeSideDish>
    <fr:recipeOrigin/>
    <fr:recipeSeeAlso/>
    <fr:recipeLicense/>
</fr:recipe>
