<?xml version="1.0" encoding="UTF-8"?><!DOCTYPE stylesheet SYSTEM "file:///C:/Users/nlutt/Documents/Websites/tools/entities.dtd"><fr:recipe xmlns:fr="http://fruschtique.de/ns/recipe" xmlns:xsi="http://www.w3.org/2001/XMLSchema-instance" xsi:schemaLocation="http://fruschtique.de/ns/recipe ../../../tools/recipe.xsd" rcpID="fr-55975a67-3145-4ae7-bac3-22aab4b0e4a2">
<fr:meta><fr:book>kochbuch</fr:book><fr:chapter>01 Grundrezepte</fr:chapter></fr:meta><fr:recipeName>Consommé double</fr:recipeName><fr:recipeKeywords>Rindfleisch,Sellerie,Karotten,Zimt</fr:recipeKeywords><fr:recipeIntro><fr:introText>Consommé double – das ist Fleischbrühe at its best! (Wahrscheinlich ist die nur in Schwaben gebräuchliche Fleischbrühtasch eigens für den Zweck erfunden worden, einen ordentlichen Topf Consommé double immer dabei haben zu können …) Mit ein paar feinen Gemüsestreifen drin kann man sie prima vor einem Menu als eleganten Magenwärmer reichen. Noch besser: Die Consommé double mit einer rote Bete und einem kleinen bisschen Knoblauch zu einem Borschtsch machen. Wow!</fr:introText><fr:introText>Die Zutaten ergeben ca. 2 l Consommé double.</fr:introText></fr:recipeIntro><fr:recipeIngredients><fr:igdtList><fr:igdtListName>Fleischbrühe</fr:igdtListName><fr:igdtListLine><fr:igdtQuantity>1 kg</fr:igdtQuantity><fr:igdtName ref="fleisch">Suppenfleisch, gemischt mit und ohne Knochen</fr:igdtName></fr:igdtListLine><fr:igdtListLine><fr:igdtQuantity>1</fr:igdtQuantity><fr:igdtName ref="zwiebel">Zwiebel</fr:igdtName></fr:igdtListLine><fr:igdtListLine><fr:igdtQuantity>2</fr:igdtQuantity><fr:igdtName ref="karotte">Karotten</fr:igdtName></fr:igdtListLine><fr:igdtListLine><fr:igdtQuantity>1 Stück</fr:igdtQuantity><fr:igdtName ref="knollensellerie">Knollensellerie</fr:igdtName></fr:igdtListLine><fr:igdtListLine><fr:igdtQuantity>1 Stange</fr:igdtQuantity><fr:igdtName ref="staudensellerie">Staudensellerie</fr:igdtName></fr:igdtListLine><fr:igdtListLine><fr:igdtQuantity>1 Stange</fr:igdtQuantity><fr:igdtName ref="lauch">Lauch</fr:igdtName></fr:igdtListLine><fr:igdtListLine><fr:igdtQuantity>2</fr:igdtQuantity><fr:igdtName ref="petersilienwurzel">Petersilienwurzeln</fr:igdtName></fr:igdtListLine><fr:igdtListLine><fr:igdtQuantity>3</fr:igdtQuantity><fr:igdtName ref="knoblauch">Knoblauchzehen</fr:igdtName></fr:igdtListLine><fr:igdtListLine><fr:igdtQuantity>1 Zweig</fr:igdtQuantity><fr:igdtName ref="thymian">Thymian</fr:igdtName></fr:igdtListLine><fr:igdtListLine><fr:igdtQuantity>1</fr:igdtQuantity><fr:igdtName ref="lorbeer">Lorbeerblatt</fr:igdtName></fr:igdtListLine><fr:igdtListLine><fr:igdtQuantity>1</fr:igdtQuantity><fr:igdtName ref="nelke">Nelke</fr:igdtName></fr:igdtListLine><fr:igdtListLine><fr:igdtQuantity>1 Msp.</fr:igdtQuantity><fr:igdtName ref="zimt">Zimt</fr:igdtName></fr:igdtListLine><fr:igdtListLine><fr:igdtQuantity>10</fr:igdtQuantity><fr:igdtName ref="pfeffer">Pfefferkörner</fr:igdtName></fr:igdtListLine><fr:igdtListLine><fr:igdtQuantity></fr:igdtQuantity><fr:igdtName ref="">Salz</fr:igdtName></fr:igdtListLine></fr:igdtList><fr:igdtList><fr:igdtListName>Klärfleisch</fr:igdtListName><fr:igdtListLine><fr:igdtQuantity>4</fr:igdtQuantity><fr:igdtName ref="ei">Eier</fr:igdtName></fr:igdtListLine><fr:igdtListLine><fr:igdtQuantity>300 g</fr:igdtQuantity><fr:igdtName ref="hackfleisch">Rinderhack</fr:igdtName></fr:igdtListLine><fr:igdtListLine><fr:igdtQuantity>100 g</fr:igdtQuantity><fr:igdtName ref="suppengemüse">Wurzelgemüse</fr:igdtName></fr:igdtListLine><fr:igdtListLine><fr:igdtQuantity>1</fr:igdtQuantity><fr:igdtName ref="lorbeer">Lorbeerblatt</fr:igdtName></fr:igdtListLine><fr:igdtListLine><fr:igdtQuantity></fr:igdtQuantity><fr:igdtName ref="liebstöckel">Liebstöckel</fr:igdtName></fr:igdtListLine><fr:igdtListLine><fr:igdtQuantity></fr:igdtQuantity><fr:igdtName ref="rosmarin">Rosmarin</fr:igdtName></fr:igdtListLine><fr:igdtListLine><fr:igdtQuantity></fr:igdtQuantity><fr:igdtName ref="majoran">Majoran</fr:igdtName></fr:igdtListLine><fr:igdtListLine><fr:igdtQuantity>1 EL</fr:igdtQuantity><fr:igdtName ref="sherry">Sherry</fr:igdtName></fr:igdtListLine><fr:igdtListLine><fr:igdtQuantity>10</fr:igdtQuantity><fr:igdtName ref="pfeffer">Pfefferkörner</fr:igdtName></fr:igdtListLine><fr:igdtListLine><fr:igdtQuantity></fr:igdtQuantity><fr:igdtName ref="">Salz</fr:igdtName></fr:igdtListLine></fr:igdtList></fr:recipeIngredients><fr:recipeInstructions><fr:instruction><fr:instrStepName>Fleischbrühe</fr:instrStepName><fr:instrStepText>Das Suppenfleisch kalt abbrausen und in einem Topf mit kaltem Wasser bedecken, ca. 2 l. Zum Kochen bringen, Salz hinzugeben und ca. 1 h leise köcheln lassen (1 Bläschen/min …)</fr:instrStepText><fr:instrStepText>Die ungeschälte Zwiebel quer halbieren und in einer beschichteten Pfanne ohne Fett braten, bis die Schnittfläche braun gefärbt ist. Gemüse putzen. Knoblauch schälen und mit einer Messerklinge andrücken.</fr:instrStepText><fr:instrStepText>Alle Zutaten zum Fleisch geben. Evtl. noch etwas kaltes Wasser nachfüllen, so daß alle Zutaten bedeckt sind. Die Brühe eine weitere h leise kochen lassen. Dann durch ein Sieb passieren, evtl. mit etwas Salz abschmecken und abkühlen lassen.</fr:instrStepText><fr:instrStepText>Die abgekühlte Brühe mit Küchenpapier entfetten.</fr:instrStepText></fr:instruction><fr:instruction><fr:instrStepName>Klären</fr:instrStepName><fr:instrStepText>Das Klärfleisch mit den Eiweiß von vier Eiern, dem Pfeffer, den Kräutern und dem Salz kräftig vermischen. In einen Suppentopf geben und die gekühlte Fleischbrühe darüber giessen. Gut verrühren.</fr:instrStepText><fr:instrStepText>Bei mittlerer Hitze einmal aufkochen, dabei immer wieder rühren, damit am Topfboden nichts ansetzt. Sobald das Fleischgemisch nach oben aufschwimmt, aufbricht und Schaum aus den Rissen im Fleischkuchen austritt, sofort auf kleine Temperatur schalten und keinesfalls mehr rühren!</fr:instrStepText><fr:instrStepText>30 min ziehen lassen und dann das Ganze durch ein Passiertuch passieren. Mit Sherry abschmecken.</fr:instrStepText></fr:instruction></fr:recipeInstructions><fr:recipeSideDish></fr:recipeSideDish><fr:recipeOrigin>Das Rezept für die Rinderbrühe habe ich im wesentlichen aus Christian Rachs Kochgesetzbuch übernommen. Meine Modifikationen: Rach verlangt 1 kg Fleisch pro 1 l Brühe. Der Citti-Metzger hat mich eines Besseren belehrt: Es reichen 500 g Fleisch pro 1 l Brühe – und das ist immer noch sehr üppig gerechnet. Außerdem habe ich die Anzahl der Karotten verdoppelt, statt der Petersilienstiele verwende ich Petersilienwurzeln, und außerdem füge ich noch eine Msp. Zimt hinzu – letzteres habe ich von einer Schwäbin gelernt, die höchstselbst mit einer Fleischbrühtasch ausgestattet war … Die Beschreibung des Klärvorgangs habe ich von lamiacucina übernommen. Robert Sprenger sagt: „[Durch die Klärung](https://lamiacucina.blog/2012/11/23/consommee-double-doppelte-kraftbruhe/) muss jede Brühe hindurch, wenn sie das Prädikat “doppelt” tragen will.“ Recht hat er!</fr:recipeOrigin><fr:recipeSeeAlso></fr:recipeSeeAlso><fr:recipeLicense></fr:recipeLicense></fr:recipe>